tlscanary/__init__.py
tlscanary/loader.py
tlscanary/main.py
tlscanary/report.py
tlscanary/runlog.py
tlscanary/sources_db.py
tlscanary/worker_pool.py
tlscanary/default_profile/SecurityPreloadState.txt
tlscanary/default_profile/SiteSecurityServiceState.txt
tlscanary/default_profile/cert8.db
tlscanary/default_profile/cert9.db
tlscanary/default_profile/key3.db
tlscanary/default_profile/key4.db
tlscanary/default_profile/pkcs11.txt
tlscanary/default_profile/revocations.txt
tlscanary/js/scan_worker.js
tlscanary/js/worker_common.js
tlscanary/modes/__init__.py
tlscanary/modes/basemode.py
tlscanary/modes/log.py
tlscanary/modes/performance.py
tlscanary/modes/regression.py
tlscanary/modes/scan.py
tlscanary/modes/sourceupdate.py
tlscanary/scheduler/__init__.py
tlscanary/scheduler/main.py
tlscanary/scheduler/matplotlib_agg.py
tlscanary/sources/debug.csv
tlscanary/sources/debug2.csv
tlscanary/sources/digicert.csv
tlscanary/sources/revoked.csv
tlscanary/sources/smoke_list.csv
tlscanary/sources/test_url_list.csv
tlscanary/sources/top_sites.csv
tlscanary/template/index.htm
tlscanary/template/report_template.htm
tlscanary/template/css/index_styles.css
tlscanary/template/css/ui_style.css
tlscanary/template/img/favicon.svg
tlscanary/template/img/logo.svg
tlscanary/template/js/index_page.js
tlscanary/template/js/index_transform.json
tlscanary/template/js/report_page.js
tlscanary/template/js/transform.json
tlscanary/tools/__init__.py
tlscanary/tools/cache.py
tlscanary/tools/cert.py
tlscanary/tools/cleanup.py
tlscanary/tools/firefox_app.py
tlscanary/tools/firefox_downloader.py
tlscanary/tools/firefox_extractor.py
tlscanary/tools/one_crl_downloader.py
tlscanary/tools/progress.py
tlscanary/tools/tags_db.py
tlscanary/tools/xpcshell_worker.py
tlscanary-4.0.2.dist-info/LICENSE.txt
tlscanary-4.0.2.dist-info/METADATA
tlscanary-4.0.2.dist-info/WHEEL
tlscanary-4.0.2.dist-info/entry_points.txt
tlscanary-4.0.2.dist-info/top_level.txt
tlscanary-4.0.2.dist-info/RECORD
