Metadata-Version: 2.1
Name: tlscanary
Version: 4.0.2
Summary: TLS/SSL Test Suite for Mozilla Firefox
Home-page: https://github.com/mozilla/tls-canary
Download-URL: https://github.com/mozilla/tls-canary/archive/latest.tar.gz
Author: Christiane Ruetten
Author-email: cr@mozilla.com
License: MPL2
Keywords: mozilla,firefox,tls,regression-testing,testing
Classifier: Environment :: Console
Classifier: Development Status :: 7 - Inactive
Classifier: Intended Audience :: Developers
Classifier: License :: OSI Approved :: Mozilla Public License 2.0 (MPL 2.0)
Classifier: Natural Language :: English
Classifier: Operating System :: MacOS :: MacOS X
Classifier: Operating System :: Microsoft :: Windows :: Windows 10
Classifier: Operating System :: Microsoft :: Windows :: Windows 7
Classifier: Operating System :: Microsoft :: Windows :: Windows 8
Classifier: Operating System :: Microsoft :: Windows :: Windows 8.1
Classifier: Operating System :: POSIX :: Linux
Classifier: Programming Language :: Python :: 3 :: Only
Classifier: Programming Language :: Python :: 3.6
Classifier: Programming Language :: Python :: 3.7
Classifier: Topic :: Software Development :: Quality Assurance
Classifier: Topic :: Software Development :: Testing
License-File: LICENSE.txt
Requires-Dist: coloredlogs
Requires-Dist: cryptography
Requires-Dist: hashfs
Requires-Dist: python-dateutil
Requires-Dist: worq
Provides-Extra: dev
Requires-Dist: coverage ; extra == 'dev'
Requires-Dist: pycodestyle ; extra == 'dev'
Requires-Dist: pytest ; extra == 'dev'
Requires-Dist: pytest-pycodestyle ; extra == 'dev'
Requires-Dist: pytest-runner ; extra == 'dev'
Requires-Dist: matplotlib ; extra == 'dev'
Requires-Dist: schedule ; extra == 'dev'
Provides-Extra: scheduler
Requires-Dist: matplotlib ; extra == 'scheduler'
Requires-Dist: schedule ; extra == 'scheduler'
